examples/rx_tx_loop.py
ataraxis_transport_layer_pc/__init__.py
ataraxis_transport_layer_pc/helper_modules.py
ataraxis_transport_layer_pc/py.typed
ataraxis_transport_layer_pc/transport_layer.py
ataraxis_transport_layer_pc-2.0.0.dist-info/METADATA
ataraxis_transport_layer_pc-2.0.0.dist-info/WHEEL
ataraxis_transport_layer_pc-2.0.0.dist-info/entry_points.txt
ataraxis_transport_layer_pc-2.0.0.dist-info/licenses/LICENSE
ataraxis_transport_layer_pc-2.0.0.dist-info/RECORD
