Metadata-Version: 2.4
Name: ataraxis-transport-layer-pc
Version: 2.0.0
Summary: Provides methods for establishing and maintaining bidirectional communication with Arduino and Teensy microcontrollers over USB or UART serial interfaces.
Project-URL: Homepage, https://github.com/Sun-Lab-NBB/ataraxis-transport-layer-pc
Project-URL: Documentation, https://ataraxis-transport-layer-pc-api-docs.netlify.app/
Author: Ivan Kondratyev, Katlynn Ryu
Maintainer-email: Ivan Kondratyev <ik278@cornell.edu>
License:                     GNU GENERAL PUBLIC LICENSE
License-File: LICENSE
Keywords: UART,USB,ataraxis,communication,serial
Classifier: Development Status :: 5 - Production/Stable
Classifier: Intended Audience :: Developers
Classifier: License :: OSI Approved :: GNU General Public License v3 or later (GPLv3+)
Classifier: Operating System :: MacOS :: MacOS X
Classifier: Operating System :: Microsoft :: Windows
Classifier: Operating System :: POSIX :: Linux
Classifier: Programming Language :: Python :: 3.11
Classifier: Programming Language :: Python :: 3.12
Classifier: Programming Language :: Python :: 3.13
Classifier: Topic :: Communications
Classifier: Typing :: Typed
Requires-Python: <3.14,>=3.11
Requires-Dist: ataraxis-base-utilities<4,>=3
Requires-Dist: ataraxis-time<4,>=3
Requires-Dist: intel-cmplr-lib-rt<2026,>=2025; platform_machine == 'x86_64'
Requires-Dist: numba<1,>=0
Requires-Dist: numpy<3,>=2
Requires-Dist: pyserial<4,>=3
Provides-Extra: dev
Requires-Dist: ataraxis-automation<7,>=6.0.1; extra == 'dev'
Requires-Dist: tox-uv<2,>=1; extra == 'dev'
Requires-Dist: tox<5,>=4; extra == 'dev'
Requires-Dist: types-pyserial<4,>=3; extra == 'dev'
Requires-Dist: uv<1,>=0; extra == 'dev'
